[
  {
    "key": "datr",
    "value": "7SR5aCWKXWmrrR9_R2TJA-WW",
    "domain": "facebook.com",
    "path": "/",
    "hostOnly": false,
    "creation": "2025-07-24T09:55:43.054Z",
    "lastAccessed": "2025-07-24T09:55:44.795Z"
  },
  {
    "key": "sb",
    "value": "7SR5aCDoF-Hbxr_OiSg5OOnh",
    "domain": "facebook.com",
    "path": "/",
    "hostOnly": false,
    "creation": "2025-07-24T09:55:43.069Z",
    "lastAccessed": "2025-07-24T09:55:44.795Z"
  },
  {
    "key": "locale",
    "value": "en_GB",
    "domain": "facebook.com",
    "path": "/",
    "hostOnly": false,
    "creation": "2025-07-24T09:55:43.070Z",
    "lastAccessed": "2025-07-24T09:55:44.795Z"
  },
  {
    "key": "vpd",
    "value": "v1%3B1010x501x2.15625",
    "domain": "facebook.com",
    "path": "/",
    "hostOnly": false,
    "creation": "2025-07-24T09:55:43.072Z",
    "lastAccessed": "2025-07-24T09:55:44.795Z"
  },
  {
    "key": "dpr",
    "value": "2.15625",
    "domain": "facebook.com",
    "path": "/",
    "hostOnly": false,
    "creation": "2025-07-24T09:55:43.073Z",
    "lastAccessed": "2025-07-24T09:55:44.795Z"
  },
  {
    "key": "ps_l",
    "value": "1",
    "domain": "facebook.com",
    "path": "/",
    "hostOnly": false,
    "creation": "2025-07-24T09:55:43.074Z",
    "lastAccessed": "2025-07-24T09:55:44.795Z"
  },
  {
    "key": "ps_n",
    "value": "1",
    "domain": "facebook.com",
    "path": "/",
    "hostOnly": false,
    "creation": "2025-07-24T09:55:43.074Z",
    "lastAccessed": "2025-07-24T09:55:44.795Z"
  },
  {
    "key": "m_pixel_ratio",
    "value": "2.15625",
    "domain": "facebook.com",
    "path": "/",
    "hostOnly": false,
    "creation": "2025-07-24T09:55:43.075Z",
    "lastAccessed": "2025-07-24T09:55:44.795Z"
  },
  {
    "key": "c_user",
    "value": "61573781756198",
    "domain": "facebook.com",
    "path": "/",
    "hostOnly": false,
    "creation": "2025-07-24T09:55:43.075Z",
    "lastAccessed": "2025-07-24T09:55:44.795Z"
  },
  {
    "key": "xs",
    "value": "10%3ASrg0ocflaTCU3w%3A2%3A1752834728%3A-1%3A-1",
    "domain": "facebook.com",
    "path": "/",
    "hostOnly": false,
    "creation": "2025-07-24T09:55:43.076Z",
    "lastAccessed": "2025-07-24T09:55:44.795Z"
  },
  {
    "key": "pas",
    "value": "100058914930837%3AbSGgskNMSa%2C61578322535110%3AV0QleIpH2j%2C61573781756198%3AvG0eCTVjjZ",
    "domain": "facebook.com",
    "path": "/",
    "hostOnly": false,
    "creation": "2025-07-24T09:55:43.076Z",
    "lastAccessed": "2025-07-24T09:55:44.795Z"
  },
  {
    "key": "fbl_st",
    "value": "101426050%3BT%3A29213914",
    "domain": "facebook.com",
    "path": "/",
    "hostOnly": false,
    "creation": "2025-07-24T09:55:43.077Z",
    "lastAccessed": "2025-07-24T09:55:44.795Z"
  },
  {
    "key": "wl_cbv",
    "value": "v2%3Bclient_version%3A2873%3Btimestamp%3A1752834844",
    "domain": "facebook.com",
    "path": "/",
    "hostOnly": false,
    "creation": "2025-07-24T09:55:43.077Z",
    "lastAccessed": "2025-07-24T09:55:44.795Z"
  },
  {
    "key": "fr",
    "value": "19yO0moPEpw8Zl7Cb.AWe5cuMC3C_lmB_0e0F6estnxzm0wJCEs6wrRZ3qF6BfrdgZOt8.Boeh4G..AAA.0.0.BoggMg.AWcn5ckCMqFSfU2IHrzTpS_j-tM",
    "expires": "2025-10-22T09:55:44.000Z",
    "maxAge": 7776000,
    "domain": "facebook.com",
    "path": "/",
    "secure": true,
    "httpOnly": true,
    "hostOnly": false,
    "creation": "2025-07-24T09:55:43.078Z",
    "lastAccessed": "2025-07-24T09:55:44.795Z"
  },
  {
    "key": "wd",
    "value": "980x1974",
    "domain": "facebook.com",
    "path": "/",
    "hostOnly": false,
    "creation": "2025-07-24T09:55:43.078Z",
    "lastAccessed": "2025-07-24T09:55:44.795Z"
  },
  {
    "key": "presence",
    "value": "C%7B%22t3%22%3A%5B%5D%2C%22utc3%22%3A1752834976284%2C%22v%22%3A1%7D",
    "domain": "facebook.com",
    "path": "/",
    "hostOnly": false,
    "creation": "2025-07-24T09:55:43.079Z",
    "lastAccessed": "2025-07-24T09:55:44.795Z"
  }
]